geoffrey_pylint-0.0.3.dist-info/DESCRIPTION.rst
geoffrey_pylint-0.0.3.dist-info/RECORD
geoffrey_pylint-0.0.3.dist-info/WHEEL
geoffrey_pylint-0.0.3.dist-info/top_level.txt
geoffrey_pylint-0.0.3.dist-info/metadata.json
geoffrey_pylint-0.0.3.dist-info/METADATA
geoffreplugins/pylint.py
geoffreplugins/__init__.py
geoffreyplugins/pylint.py
geoffreyplugins/__init__.py
geoffreyplugins/pylint/main.js
geoffreyplugins/pylint/assets/panel.html
geoffreyplugins/pylint/assets/.gitkeep
