Metadata-Version: 2.0
Name: geoffrey-pylint
Version: 0.0.3
Summary: python code static checker
Home-page: https://github.com/GeoffreyCI/geoffrey-pylint
Author: Roberto Abdelkader Martínez Pérez
Author-email: robertomartinezp@gmail.com
License: UNKNOWN
Platform: UNKNOWN
